mypythonanywhere/__init__.py
mypythonanywhere/friendly_pythonanywhere.py
mypythonanywhere/py.typed
mypythonanywhere/pythonanywhere.py
mypythonanywhere/clients/__init__.py
mypythonanywhere/clients/always_on.py
mypythonanywhere/clients/console.py
mypythonanywhere/clients/cpu.py
mypythonanywhere/clients/default_python.py
mypythonanywhere/clients/file.py
mypythonanywhere/clients/schedule.py
mypythonanywhere/types/__init__.py
mypythonanywhere/types/account_type.py
mypythonanywhere/types/base_request.py
mypythonanywhere/types/custom_type_alias.py
mypythonanywhere/types/request_method.py
mypythonanywhere/types/models/__init__.py
mypythonanywhere/types/models/console.py
mypythonanywhere/types/models/cpu.py
mypythonanywhere/types/models/file_shared.py
mypythonanywhere/types/models/file_uploaded.py
mypythonanywhere/types/models/interval_type.py
mypythonanywhere/types/models/path_info.py
mypythonanywhere/types/models/python_version.py
mypythonanywhere/types/models/schedule_task.py
mypythonanywhere/types/requests/__init__.py
mypythonanywhere/types/requests/always_on.py
mypythonanywhere/types/requests/console.py
mypythonanywhere/types/requests/cpu.py
mypythonanywhere/types/requests/default_python.py
mypythonanywhere/types/requests/file.py
mypythonanywhere/types/requests/schedule.py
mypythonanywhere-0.1.5rc0.dist-info/LICENSE
mypythonanywhere-0.1.5rc0.dist-info/METADATA
mypythonanywhere-0.1.5rc0.dist-info/WHEEL
mypythonanywhere-0.1.5rc0.dist-info/top_level.txt
mypythonanywhere-0.1.5rc0.dist-info/RECORD
