Metadata-Version: 2.1
Name: mypythonanywhere
Version: 0.1.5rc0
Summary: A python wrapper for the pythonanywhere.com API
Home-page: https://github.com/immmdreza/mypythonanywhere
Author: immmdreza
Author-email: ir310022@gmail.com
License: UNKNOWN
Project-URL: Bug Tracker, https://github.com/immmdreza/mypythonanywhere/issues
Platform: UNKNOWN
Classifier: Programming Language :: Python :: 3
Classifier: License :: OSI Approved :: MIT License
Classifier: Operating System :: OS Independent
Requires-Python: >=3.10
License-File: LICENSE
Requires-Dist: aiodns (==3.0.0)
Requires-Dist: aiohttp (==3.8.1)
Requires-Dist: python-dotenv (==0.20.0)
